py2sfn_task_tools/__init__.py
py2sfn_task_tools/context.py
py2sfn_task_tools/exceptions.py
py2sfn_task_tools/state_data_client.py
py2sfn_task_tools/stop_execution.py
py2sfn_task_tools-1.0.2.dist-info/LICENSE.md
py2sfn_task_tools-1.0.2.dist-info/WHEEL
py2sfn_task_tools-1.0.2.dist-info/METADATA
py2sfn_task_tools-1.0.2.dist-info/RECORD
