Metadata-Version: 2.1
Name: py2sfn-task-tools
Version: 1.0.2
Summary: Tools for tasks embedded in an AWS Step Functions state machine. This is a helper library for py2sfn.
Home-page: https://github.com/NarrativeScience/py2sfn-task-tools
License: BSD-3-Clause
Author: Jonathan Drake
Author-email: jdrake@narrativescience.com
Requires-Python: >=3.7,<4
Classifier: License :: OSI Approved :: BSD License
Classifier: Programming Language :: Python :: 3
Classifier: Programming Language :: Python :: 3.7
Classifier: Programming Language :: Python :: 3.8
Classifier: Programming Language :: Python :: 3.9
Classifier: Programming Language :: Python :: 3.10
Classifier: Programming Language :: Python :: 3.11
Requires-Dist: backoff (>=2.2.1,<3.0.0)
Requires-Dist: boto3 (>=1.24.59,<2.0.0)
Requires-Dist: sfn-workflow-client (>=1.1.1,<2.0.0)
Project-URL: Repository, https://github.com/NarrativeScience/py2sfn-task-tools
